bomiot_test1/__init__.py
bomiot_test1/__version__.py
bomiot_test1/bomiotconf.ini
bomiot_test1/language/__init__.py
bomiot_test1/language/en-US.toml
bomiot_test1/language/zh-CN.toml
bomiot_test1/media/__init__.py
bomiot_test1/media/README.md
bomiot_test1/receiver.py
bomiot_test1/templates/.editorconfig
bomiot_test1/templates/.gitignore
bomiot_test1/templates/.npmrc
bomiot_test1/templates/.prettierrc.json
bomiot_test1/templates/dist/spa/assets/_commonjsHelpers-Cpj98o6Y.js
bomiot_test1/templates/dist/spa/assets/APIReader-JDhwoGxI.js
bomiot_test1/templates/dist/spa/assets/axios-CxvZFXbF.js
bomiot_test1/templates/dist/spa/assets/ClosePopup-_moYH0Ql.js
bomiot_test1/templates/dist/spa/assets/CPUReader-BZqwp1gy.js
bomiot_test1/templates/dist/spa/assets/DepartmentReader-CYWerjQ7.js
bomiot_test1/templates/dist/spa/assets/DiskReader-BXKDEAon.js
bomiot_test1/templates/dist/spa/assets/DocCenter-CY9iYII7.js
bomiot_test1/templates/dist/spa/assets/ErrorNotFound-DbiolJsB.js
bomiot_test1/templates/dist/spa/assets/ExampleReader-ClrksHe5.js
bomiot_test1/templates/dist/spa/assets/flUhRq6tzZclQEJ-Vdg-IuiaDsNa-Dr0goTwe.woff
bomiot_test1/templates/dist/spa/assets/flUhRq6tzZclQEJ-Vdg-IuiaDsNcIhQ8tQ-D-x-0Q06.woff2
bomiot_test1/templates/dist/spa/assets/i18n-Fq28SuGf.js
bomiot_test1/templates/dist/spa/assets/index-CgJpg41F.css
bomiot_test1/templates/dist/spa/assets/index-CpxCXuaf.js
bomiot_test1/templates/dist/spa/assets/IndexPage-XgF4Bab_.js
bomiot_test1/templates/dist/spa/assets/installCanvasRenderer-LYN4AL6A.js
bomiot_test1/templates/dist/spa/assets/KFOkCnqEu92Fr1MmgVxIIzQ-Y2mpUUkw.woff
bomiot_test1/templates/dist/spa/assets/KFOlCnqEu92Fr1MmEU9fBBc--ViM7Ag4Q.woff
bomiot_test1/templates/dist/spa/assets/KFOlCnqEu92Fr1MmSU5fBBc--CrFzpgl6.woff
bomiot_test1/templates/dist/spa/assets/KFOlCnqEu92Fr1MmWUlfBBc--CW3_XjG_.woff
bomiot_test1/templates/dist/spa/assets/KFOlCnqEu92Fr1MmYUtfBBc--Dr8fnyGc.woff
bomiot_test1/templates/dist/spa/assets/KFOmCnqEu92Fr1Mu4mxM-DAYh6T4l.woff
bomiot_test1-0.7.0.dist-info/entry_points.txt
bomiot_test1-0.7.0.dist-info/LICENSE
bomiot_test1-0.7.0.dist-info/METADATA
bomiot_test1-0.7.0.dist-info/WHEEL
bomiot_test1-0.7.0.dist-info/RECORD
